kwnn/__init__.py
kwnn/_client.py
kwnn/_exception.py
kwnn/_models.py
kwnn/_resource.py
kwnn/_version.py
kwnn/version.py
kwnn/resources/__init__.py
kwnn/resources/chat/__init__.py
kwnn/resources/chat/chat.py
kwnn/resources/chat/completions.py
kwnn/types/__init__.py
kwnn/types/chat/__init__.py
kwnn/types/chat/chat_completion.py
kwnn/types/chat/chat_completion_chunk.py
kwnn-1.0.6.dist-info/METADATA
kwnn-1.0.6.dist-info/WHEEL
kwnn-1.0.6.dist-info/licenses/LICENSE
kwnn-1.0.6.dist-info/RECORD
